tboxsdk/__init__.py
tboxsdk/tbox.py
tboxsdk/core/__init__.py
tboxsdk/core/exception.py
tboxsdk/core/httpclient.py
tboxsdk/model/__init__.py
tboxsdk/model/conversation.py
tboxsdk/model/file.py
tboxsdk/model/message.py
tboxsdk-0.0.10.dist-info/METADATA
tboxsdk-0.0.10.dist-info/WHEEL
tboxsdk-0.0.10.dist-info/top_level.txt
tboxsdk-0.0.10.dist-info/RECORD
