Metadata-Version: 2.4
Name: tboxsdk
Version: 0.0.10
Summary: Common functions to interact with Tbox
Home-page: https://code.alipay.com/ai_release/tboxsdk-python
Author: 久知
Author-email: haoxuan.yhx@antgroup.com
Classifier: Programming Language :: Python :: 3
Classifier: License :: OSI Approved :: MIT License
Classifier: Operating System :: OS Independent
Requires-Python: >=3.6
Requires-Dist: httpx
Requires-Dist: sseclient-py
Dynamic: author
Dynamic: author-email
Dynamic: classifier
Dynamic: description
Dynamic: description-content-type
Dynamic: home-page
Dynamic: requires-dist
Dynamic: requires-python
Dynamic: summary
